{
  "id": "apple-noida",
  "storeNumber": "R787",
  "name": {
    "en": "Apple Noida",
    "fr": "Apple Noida"
  },
  "status": "open",
  "city": "Noida",
  "region": "Uttar Pradesh",
  "countryCode": "IN",
  "countryName": "India",
  "address": "D123-D128, DLF Mall of India Sector 18, 201301, Noida, Uttar Pradesh",
  "coordinates": {
    "latitude": 28.56724,
    "longitude": 77.32164
  },
  "openedOn": "2025-12-11",
  "closedOn": null,
  "officialUrl": "https://www.apple.com/in/retail/noida/",
  "architecture": {
    "era": "Unknown",
    "typology": "Unknown",
    "attributes": {
      "avenue": "unknown",
      "boardroom": "unknown",
      "forum": "unknown",
      "geniusBar": "unknown",
      "glassCube": "unknown",
      "greenWall": "unknown",
      "historicFacade": "unknown",
      "outdoor": "unknown",
      "pickup": "unknown",
      "plaza": "unknown",
      "trees": "unknown",
      "videoWall": "unknown"
    }
  },
  "hours": {
    "policy": "official-link-only",
    "officialUrl": "https://www.apple.com/in/retail/noida/",
    "lastVerifiedAt": null,
    "note": "Hours change often. Verify on the official Apple page before visiting."
  },
  "photos": [],
  "lastVerifiedAt": "2026-05-17"
}
