{
  "id": "apple-atlantis",
  "storeNumber": "R470",
  "name": {
    "en": "Apple Atlantis",
    "fr": "Apple Atlantis"
  },
  "status": "open",
  "city": "Saint Herblain",
  "region": "Loire-Atlantique",
  "countryCode": "FR",
  "countryName": "France",
  "address": "Galerie Atlantis Le Centre, 44811, Saint Herblain, Loire-Atlantique",
  "coordinates": {
    "latitude": 47.225393,
    "longitude": -1.630539
  },
  "openedOn": "2012-11-15",
  "closedOn": null,
  "officialUrl": "https://www.apple.com/fr/retail/atlantis/",
  "architecture": {
    "era": "Unknown",
    "typology": "Classic",
    "attributes": {
      "avenue": "no",
      "boardroom": "no",
      "forum": "no",
      "geniusBar": "yes",
      "glassCube": "unknown",
      "greenWall": "no",
      "historicFacade": "unknown",
      "outdoor": "no",
      "pickup": "no",
      "plaza": "no",
      "trees": "no",
      "videoWall": "unknown"
    }
  },
  "hours": {
    "policy": "official-link-only",
    "officialUrl": "https://www.apple.com/fr/retail/atlantis/",
    "lastVerifiedAt": null,
    "note": "Hours change often. Verify on the official Apple page before visiting."
  },
  "photos": [],
  "lastVerifiedAt": "2026-05-18"
}
