{
  "id": "apple-eaton-centre",
  "storeNumber": "R121",
  "name": {
    "en": "Apple Eaton Centre",
    "fr": "Apple Eaton Centre"
  },
  "status": "open",
  "city": "Toronto",
  "region": "Ontario",
  "countryCode": "CA",
  "countryName": "Canada",
  "address": "220 Yonge Street, Toronto, ON M5B 2H1",
  "coordinates": {
    "latitude": 43.653,
    "longitude": -79.3804
  },
  "openedOn": "2006-05-06",
  "closedOn": null,
  "officialUrl": "https://www.apple.com/ca/retail/eatoncentre/",
  "architecture": {
    "era": "Unknown",
    "typology": "NSD",
    "attributes": {
      "avenue": "yes",
      "boardroom": "no",
      "forum": "yes",
      "geniusBar": "yes",
      "glassCube": "unknown",
      "greenWall": "no",
      "historicFacade": "unknown",
      "outdoor": "no",
      "pickup": "no",
      "plaza": "no",
      "trees": "no",
      "videoWall": "unknown"
    }
  },
  "hours": {
    "policy": "official-link-only",
    "officialUrl": "https://www.apple.com/ca/retail/eatoncentre/",
    "lastVerifiedAt": null,
    "note": "Hours change often. Verify on the official Apple page before visiting."
  },
  "photos": [],
  "lastVerifiedAt": "2026-05-18"
}
