{
  "id": "apple-tower-theatre",
  "storeNumber": "R720",
  "name": {
    "en": "Apple Tower Theatre",
    "fr": "Apple Tower Theatre"
  },
  "status": "open",
  "city": "Los Angeles",
  "region": "California",
  "countryCode": "US",
  "countryName": "United States",
  "address": "802 S Broadway, Los Angeles, CA 90014",
  "coordinates": {
    "latitude": 34.043549,
    "longitude": -118.254664
  },
  "openedOn": "2021-06-24",
  "closedOn": null,
  "officialUrl": "https://www.apple.com/retail/towertheatre/",
  "architecture": {
    "era": "Unknown",
    "typology": "NSD",
    "attributes": {
      "avenue": "yes",
      "boardroom": "no",
      "forum": "yes",
      "geniusBar": "yes",
      "glassCube": "unknown",
      "greenWall": "no",
      "historicFacade": "unknown",
      "outdoor": "yes",
      "pickup": "no",
      "plaza": "no",
      "trees": "no",
      "videoWall": "unknown"
    }
  },
  "hours": {
    "policy": "official-link-only",
    "officialUrl": "https://www.apple.com/retail/towertheatre/",
    "lastVerifiedAt": null,
    "note": "Hours change often. Verify on the official Apple page before visiting."
  },
  "photos": [],
  "lastVerifiedAt": "2026-05-18"
}
