{
  "id": "apple-iconsiam",
  "storeNumber": "R728",
  "name": {
    "en": "Apple Iconsiam",
    "fr": "Apple Iconsiam"
  },
  "status": "open",
  "city": "กรุงเทพมหานคร",
  "region": "กรุงเทพมหานคร",
  "countryCode": "TH",
  "countryName": "Thailand",
  "address": "299 ถนนเจริญนคร แขวงคลองต้นไทร เขตคลองสาน, 10600, กรุงเทพมหานคร",
  "coordinates": {
    "latitude": 13.726822,
    "longitude": 100.511255
  },
  "openedOn": "2018-11-10",
  "closedOn": null,
  "officialUrl": "https://www.apple.com/th/retail/iconsiam/",
  "architecture": {
    "era": "Unknown",
    "typology": "NSD",
    "attributes": {
      "avenue": "yes",
      "boardroom": "no",
      "forum": "yes",
      "geniusBar": "no",
      "glassCube": "unknown",
      "greenWall": "yes",
      "historicFacade": "unknown",
      "outdoor": "yes",
      "pickup": "no",
      "plaza": "yes",
      "trees": "yes",
      "videoWall": "unknown"
    }
  },
  "hours": {
    "policy": "official-link-only",
    "officialUrl": "https://www.apple.com/th/retail/iconsiam/",
    "lastVerifiedAt": null,
    "note": "Hours change often. Verify on the official Apple page before visiting."
  },
  "photos": [],
  "lastVerifiedAt": "2026-05-18"
}
