{
  "id": "apple-mixcnanning",
  "storeNumber": "R571",
  "name": {
    "en": "Apple 南宁万象城",
    "fr": "Apple 南宁万象城"
  },
  "status": "open",
  "city": "南宁",
  "region": "广西壮族自治区",
  "countryCode": "CN",
  "countryName": "China",
  "address": "南宁市青秀区民族大道 136 号, 530022, 广西壮族自治区",
  "coordinates": {
    "latitude": 22.813693,
    "longitude": 108.388356
  },
  "openedOn": "2015-12-12",
  "closedOn": null,
  "officialUrl": "https://www.apple.com.cn/retail/mixcnanning/",
  "architecture": {
    "era": "Unknown",
    "typology": "NSD",
    "attributes": {
      "avenue": "yes",
      "boardroom": "no",
      "forum": "yes",
      "geniusBar": "yes",
      "glassCube": "unknown",
      "greenWall": "no",
      "historicFacade": "unknown",
      "outdoor": "no",
      "pickup": "no",
      "plaza": "no",
      "trees": "no",
      "videoWall": "unknown"
    }
  },
  "hours": {
    "policy": "official-link-only",
    "officialUrl": "https://www.apple.com.cn/retail/mixcnanning/",
    "lastVerifiedAt": null,
    "note": "Hours change often. Verify on the official Apple page before visiting."
  },
  "photos": [],
  "lastVerifiedAt": "2026-05-18",
  "aliases": [
    "MixC Nanning",
    "南宁万象城"
  ]
}
