{
  "id": "apple-miranda",
  "storeNumber": "R606",
  "name": {
    "en": "Apple Miranda",
    "fr": "Apple Miranda"
  },
  "status": "open",
  "city": "Miranda",
  "region": "New South Wales",
  "countryCode": "AU",
  "countryName": "Australia",
  "address": "Westfield Miranda 600 Kingsway, 2228, New South Wales",
  "coordinates": {
    "latitude": -34.03492,
    "longitude": 151.10088
  },
  "openedOn": "2015-07-25",
  "closedOn": null,
  "officialUrl": "https://www.apple.com/au/retail/miranda/",
  "architecture": {
    "era": "Unknown",
    "typology": "Classic Upgrade",
    "attributes": {
      "avenue": "no",
      "boardroom": "no",
      "forum": "yes",
      "geniusBar": "yes",
      "glassCube": "unknown",
      "greenWall": "no",
      "historicFacade": "unknown",
      "outdoor": "no",
      "pickup": "no",
      "plaza": "no",
      "trees": "no",
      "videoWall": "unknown"
    }
  },
  "hours": {
    "policy": "official-link-only",
    "officialUrl": "https://www.apple.com/au/retail/miranda/",
    "lastVerifiedAt": null,
    "note": "Hours change often. Verify on the official Apple page before visiting."
  },
  "photos": [],
  "lastVerifiedAt": "2026-05-18"
}
